mensajes/__init__.py
mensajes/adios/__init__.py
mensajes/adios/despedidas.py
mensajes/hola/__init__.py
mensajes/hola/saludos.py
tests/__init__.py
tests/test_hola.py
mensajes_hponcedeleon-6.1.dist-info/LICENSE
mensajes_hponcedeleon-6.1.dist-info/METADATA
mensajes_hponcedeleon-6.1.dist-info/WHEEL
mensajes_hponcedeleon-6.1.dist-info/top_level.txt
mensajes_hponcedeleon-6.1.dist-info/RECORD
